practipy/__init__.py
practipy/cache.py
practipy/classes.py
practipy/gcloud.py
practipy/imports.py
practipy/iterators.py
practipy/logs.py
practipy/math.py
practipy/tensorflow.py
practipy/testing.py
practipy/text.py
practipy/typing.py
practipy-0.0.2.dist-info/LICENSE
practipy-0.0.2.dist-info/METADATA
practipy-0.0.2.dist-info/WHEEL
practipy-0.0.2.dist-info/top_level.txt
practipy-0.0.2.dist-info/RECORD
