Metadata-Version: 2.1
Name: practipy
Version: 0.0.2
Summary: Python convenience functions and classes
Home-page: UNKNOWN
Author: Jelmer Neeven
Author-email: jelmer@neeven.tech
License: MIT
Keywords: python utility practical convenience
Platform: Linux
Classifier: License :: OSI Approved :: MIT License
Classifier: Intended Audience :: Developers
Classifier: Operating System :: Unix
Classifier: Programming Language :: Python
Classifier: Programming Language :: Python :: 3.8
Classifier: Programming Language :: Python :: 3.9
Classifier: Topic :: Software Development :: Libraries :: Python Modules
License-File: LICENSE
Provides-Extra: all
Requires-Dist: black (==22.3.0) ; extra == 'all'
Requires-Dist: docformatter (==1.4) ; extra == 'all'
Requires-Dist: flake8 (==4.0.1) ; extra == 'all'
Requires-Dist: isort (==5.7.0) ; extra == 'all'
Requires-Dist: pytest (==6.2.2) ; extra == 'all'
Requires-Dist: pytest-custom-exit-code (==0.3.0) ; extra == 'all'
Requires-Dist: pytest-xdist (==2.2.1) ; extra == 'all'
Requires-Dist: pytype (==2021.8.11) ; extra == 'all'
Requires-Dist: diskcache (>=5.0) ; extra == 'all'
Requires-Dist: google-cloud-storage (>=1.38) ; extra == 'all'
Requires-Dist: tqdm (>=4.61) ; extra == 'all'
Requires-Dist: numpy ; extra == 'all'
Requires-Dist: absl-py ; extra == 'all'
Provides-Extra: cache
Requires-Dist: diskcache (>=5.0) ; extra == 'cache'
Provides-Extra: dev
Requires-Dist: black (==22.3.0) ; extra == 'dev'
Requires-Dist: docformatter (==1.4) ; extra == 'dev'
Requires-Dist: flake8 (==4.0.1) ; extra == 'dev'
Requires-Dist: isort (==5.7.0) ; extra == 'dev'
Requires-Dist: pytest (==6.2.2) ; extra == 'dev'
Requires-Dist: pytest-custom-exit-code (==0.3.0) ; extra == 'dev'
Requires-Dist: pytest-xdist (==2.2.1) ; extra == 'dev'
Requires-Dist: pytype (==2021.8.11) ; extra == 'dev'
Provides-Extra: gcloud
Requires-Dist: google-cloud-storage (>=1.38) ; extra == 'gcloud'
Requires-Dist: tqdm (>=4.61) ; extra == 'gcloud'
Provides-Extra: math
Requires-Dist: numpy ; extra == 'math'
Provides-Extra: tensorflow
Requires-Dist: absl-py ; extra == 'tensorflow'
